tests/__init__.py
tests/test_model.py
tests/utils.py
zhkeybert/__init__.py
zhkeybert/_extract_kws.py
zhkeybert/_highlight.py
zhkeybert/_maxsum.py
zhkeybert/_mmr.py
zhkeybert/_model.py
zhkeybert/backend/__init__.py
zhkeybert/backend/_base.py
zhkeybert/backend/_flair.py
zhkeybert/backend/_gensim.py
zhkeybert/backend/_sentencetransformers.py
zhkeybert/backend/_spacy.py
zhkeybert/backend/_use.py
zhkeybert/backend/_utils.py
zhkeybert-0.1.2.dist-info/LICENSE
zhkeybert-0.1.2.dist-info/METADATA
zhkeybert-0.1.2.dist-info/WHEEL
zhkeybert-0.1.2.dist-info/top_level.txt
zhkeybert-0.1.2.dist-info/RECORD
