Metadata-Version: 2.1
Name: zhkeybert
Version: 0.1.2
Summary: Based on KeyBERT performs Chinese documents keyword extraction with state-of-the-art transformer models.
Home-page: https://github.com/deepdialog/ZhKeyBERT
Author: Maarten Grootendorst, Yao Su
Author-email: maartengrootendorst@gmail.com, 1092702101@qq.com
License: UNKNOWN
Keywords: nlp bert keyword extraction embeddings for Chinese
Platform: UNKNOWN
Classifier: Programming Language :: Python
Classifier: Intended Audience :: Science/Research
Classifier: Intended Audience :: Developers
Classifier: Topic :: Scientific/Engineering :: Artificial Intelligence
Classifier: License :: OSI Approved :: MIT License
Classifier: Topic :: Scientific/Engineering
Classifier: Operating System :: Microsoft :: Windows
Classifier: Operating System :: POSIX
Classifier: Operating System :: Unix
Classifier: Operating System :: MacOS
Classifier: Programming Language :: Python :: 3.7
Classifier: Programming Language :: Python :: 3.6
Classifier: Programming Language :: Python :: 3.8
Requires-Python: >=3.6
License-File: LICENSE
Requires-Dist: jieba
Requires-Dist: sentence-transformers (>=0.3.8)
Requires-Dist: scikit-learn (>=0.22.2)
Requires-Dist: numpy (>=1.18.5)
Requires-Dist: rich (>=10.4.0)
Provides-Extra: dev
Requires-Dist: mkdocs (>=1.1) ; extra == 'dev'
Requires-Dist: mkdocs-material (>=4.6.3) ; extra == 'dev'
Requires-Dist: mkdocstrings (>=0.8.0) ; extra == 'dev'
Requires-Dist: pytest (>=5.4.3) ; extra == 'dev'
Requires-Dist: pytest-cov (>=2.6.1) ; extra == 'dev'
Provides-Extra: docs
Requires-Dist: mkdocs (>=1.1) ; extra == 'docs'
Requires-Dist: mkdocs-material (>=4.6.3) ; extra == 'docs'
Requires-Dist: mkdocstrings (>=0.8.0) ; extra == 'docs'
Provides-Extra: flair
Requires-Dist: transformers (==3.5.1) ; extra == 'flair'
Requires-Dist: torch (<1.7.1,>=1.4.0) ; extra == 'flair'
Requires-Dist: flair (==0.7) ; extra == 'flair'
Provides-Extra: test
Requires-Dist: pytest (>=5.4.3) ; extra == 'test'
Requires-Dist: pytest-cov (>=2.6.1) ; extra == 'test'
